<annotations><filename>HuvudUpph&#246;r6.JPEG</filename><folder>images</folder><size><width>900</width><height>607</height><depth>3</depth></size><object><name>VM-B5</name><pose>Unspecified</pose><truncated>0</truncated><difficult>0</difficult><bndbox><xmin>691.0</xmin><ymin>174.0</ymin><xmax>777.0</xmax><ymax>254.0</ymax></bndbox></object><object><name>VM-C31-5</name><pose>Unspecified</pose><truncated>0</truncated><difficult>0</difficult><bndbox><xmin>680.0</xmin><ymin>77.0</ymin><xmax>777.0</xmax><ymax>175.0</ymax></bndbox></object></annotations>